jess/JESS_filters.py
jess/JESS_filters_cupy.py
jess/JESS_filters_generic.py
jess/__init__.py
jess/_fdmt_utils.py
jess/_sumthreshold_utils.py
jess/_version.py
jess/calculators.py
jess/calculators_cupy.py
jess/channel_masks.py
jess/dispersion.py
jess/dispersion_cupy.py
jess/fitters.py
jess/fitters_cupy.py
jess/scipy_cupy/__init__.py
jess/scipy_cupy/stats.py
jess-0.3.1.data/scripts/channel_mask_maker.py
jess-0.3.1.data/scripts/fft_cleaner.py
jess-0.3.1.data/scripts/jess_combine_mocks.py
jess-0.3.1.data/scripts/jess_composite.py
jess-0.3.1.data/scripts/jess_gauss.py
jess-0.3.1.data/scripts/mad_filter.py
jess-0.3.1.data/scripts/mask_maker.py
jess-0.3.1.data/scripts/mask_viewer.py
jess-0.3.1.data/scripts/radiometer_calculator.py
jess-0.3.1.data/scripts/radiometer_calculator_greenburst.py
jess-0.3.1.data/scripts/rfi_viewer.py
jess-0.3.1.data/scripts/zero_dm.py
jess-0.3.1.dist-info/licenses/LICENSE.txt
tests/__init__.py
tests/test_JESS_filters.py
tests/test_JESS_filters_cupy.py
tests/test_JESS_filters_generic.py
tests/test_calculators.py
tests/test_calculators_cupy.py
tests/test_channel_masks.py
tests/test_dispersion.py
tests/test_dispersion_cupy.py
tests/test_fitters.py
tests/test_fitters_cupy.py
tests/test_stats.py
jess-0.3.1.dist-info/METADATA
jess-0.3.1.dist-info/WHEEL
jess-0.3.1.dist-info/top_level.txt
jess-0.3.1.dist-info/RECORD
